{
  "repo": "mossblaser/plottie",
  "commits": [
    {
      "sha": "a8a15182339da2ccc280b0ca47b5455d186909a2",
      "date": "2020-11-14T15:04:01Z",
      "author_login": "mossblaser",
      "author_name": "Jonathan Heathcote",
      "author_email": "mail@jhnet.co.uk",
      "files": [
        "plottie/cli.py"
      ]
    },
    {
      "sha": "7a0dc51ce593c4f8311726093af23e670d624e39",
      "date": "2020-11-14T14:58:51Z",
      "author_login": "mossblaser",
      "author_name": "Jonathan Heathcote",
      "author_email": "mail@jhnet.co.uk",
      "files": [
        "plottie/version.py"
      ]
    },
    {
      "sha": "97cdda111af49f23b2fa93d1fc799722e5e99bbf",
      "date": "2020-11-14T14:58:17Z",
      "author_login": "mossblaser",
      "author_name": "Jonathan Heathcote",
      "author_email": "mail@jhnet.co.uk",
      "files": [
        "plottie/cli.py",
        "setup.py"
      ]
    },
    {
      "sha": "541229a801709451f225f4d94c87895a371b1f26",
      "date": "2020-11-14T09:58:06Z",
      "author_login": "mossblaser",
      "author_name": "Jonathan Heathcote",
      "author_email": "mail@jhnet.co.uk",
      "files": [
        "plottie/version.py"
      ]
    },
    {
      "sha": "d81db4e8dc88c34ecd847dd74ef9c05417f7aac4",
      "date": "2020-11-14T09:57:20Z",
      "author_login": "mossblaser",
      "author_name": "Jonathan Heathcote",
      "author_email": "mail@jhnet.co.uk",
      "files": [
        "setup.py"
      ]
    },
    {
      "sha": "89b5e6f06156c96c940522d7c5b026e145a85304",
      "date": "2020-09-04T13:12:24Z",
      "author_login": "mossblaser",
      "author_name": "Jonathan Heathcote",
      "author_email": "mail@jhnet.co.uk",
      "files": [
        "plottie/version.py"
      ]
    },
    {
      "sha": "2c74c7e9eb26e91c4a40db80a540857dd7b4efe1",
      "date": "2020-09-01T13:49:38Z",
      "author_login": "mossblaser",
      "author_name": "Jonathan Heathcote",
      "author_email": "mail@jhnet.co.uk",
      "files": [
        "plottie/cli.py",
        "plottie/dummy_device.py",
        "setup.py",
        "tests/test_cli.py"
      ]
    },
    {
      "sha": "7f487a4743194fc16f14622146cfd565795cdfe6",
      "date": "2020-08-20T09:23:43Z",
      "author_login": "mossblaser",
      "author_name": "Jonathan Heathcote",
      "author_email": "mail@jhnet.co.uk",
      "files": [
        "README.md",
        "setup.py"
      ]
    },
    {
      "sha": "166c8762bafcc7b06c84f9f4178afa3271786248",
      "date": "2019-12-13T13:01:41Z",
      "author_login": "mossblaser",
      "author_name": "Jonathan Heathcote",
      "author_email": "mail@jhnet.co.uk",
      "files": [
        "plottie/version.py"
      ]
    },
    {
      "sha": "6b60c3565533adb35a9fc01105a223be798413be",
      "date": "2019-12-13T13:00:29Z",
      "author_login": "mossblaser",
      "author_name": "Jonathan Heathcote",
      "author_email": "mail@jhnet.co.uk",
      "files": [
        "plottie/cli.py",
        "plottie/over_cut.py",
        "tests/test_cli.py",
        "tests/test_over_cut.py"
      ]
    },
    {
      "sha": "26e915f0b636a263f4f2252fbd849a9a170c7108",
      "date": "2019-11-08T10:44:43Z",
      "author_login": "mossblaser",
      "author_name": "Jonathan Heathcote",
      "author_email": "mail@jhnet.co.uk",
      "files": [
        "LICENSE",
        "README.md",
        "examples/banner.png",
        "examples/cutting_example.svg",
        "examples/regmark_template.svg"
      ]
    },
    {
      "sha": "797dbd0905823e546b7ce06fa0c6a92ee88ae5c4",
      "date": "2019-11-08T08:33:20Z",
      "author_login": "mossblaser",
      "author_name": "Jonathan Heathcote",
      "author_email": "mail@jhnet.co.uk",
      "files": [
        "plottie/cli.py"
      ]
    },
    {
      "sha": "4d656a2259e6b7f6f5cf1d8b879c9f5d63d10960",
      "date": "2019-11-08T08:04:43Z",
      "author_login": "mossblaser",
      "author_name": "Jonathan Heathcote",
      "author_email": "mail@jhnet.co.uk",
      "files": [
        "tox.ini"
      ]
    },
    {
      "sha": "ebbcbbb759448ec5fe6c5655cf85f7b93cd23946",
      "date": "2019-11-08T08:04:32Z",
      "author_login": "mossblaser",
      "author_name": "Jonathan Heathcote",
      "author_email": "mail@jhnet.co.uk",
      "files": [
        "plottie/cli.py"
      ]
    },
    {
      "sha": "972c8f725b2d1195a6a4b728b0f1a313b4a1f180",
      "date": "2019-11-08T07:55:50Z",
      "author_login": "mossblaser",
      "author_name": "Jonathan Heathcote",
      "author_email": "mail@jhnet.co.uk",
      "files": [
        "setup.py"
      ]
    },
    {
      "sha": "e09b6ca6a7c0fdd4a62a7a6b40a1e7ff2f5368d7",
      "date": "2019-11-08T07:31:49Z",
      "author_login": "mossblaser",
      "author_name": "Jonathan Heathcote",
      "author_email": "mail@jhnet.co.uk",
      "files": [
        "plottie/cli.py",
        "plottie/plot_mode_heuristics.py",
        "tests/test_cli.py"
      ]
    },
    {
      "sha": "19c19d590f317ca136a230de62749f8fd3e91131",
      "date": "2019-11-06T06:51:19Z",
      "author_login": "mossblaser",
      "author_name": "Jonathan Heathcote",
      "author_email": "mail@jhnet.co.uk",
      "files": [
        "plottie/cli.py",
        "plottie/dummy_device.py",
        "tests/test_cli.py",
        "tests/test_dummy_device.py"
      ]
    },
    {
      "sha": "ccf5d90e85f5dd843b45f840efff575b2832a419",
      "date": "2019-11-05T07:15:44Z",
      "author_login": "mossblaser",
      "author_name": "Jonathan Heathcote",
      "author_email": "mail@jhnet.co.uk",
      "files": [
        "plottie/cli.py",
        "requirements-test.txt",
        "tests/test_cli.py"
      ]
    },
    {
      "sha": "22c873703622cb9d1a4c9ca59f1d2059a5273e49",
      "date": "2019-10-31T17:44:09Z",
      "author_login": "mossblaser",
      "author_name": "Jonathan Heathcote",
      "author_email": "mail@jhnet.co.uk",
      "files": [
        "setup.py"
      ]
    },
    {
      "sha": "f29f275354e95fd584ae576184bca8039aa27cd1",
      "date": "2019-10-31T17:43:20Z",
      "author_login": "mossblaser",
      "author_name": "Jonathan Heathcote",
      "author_email": "mail@jhnet.co.uk",
      "files": [
        "plottie/dummy_device.py"
      ]
    },
    {
      "sha": "66ede67f538658c8c5b6487672cac85d01ddadf2",
      "date": "2019-10-31T17:41:05Z",
      "author_login": "mossblaser",
      "author_name": "Jonathan Heathcote",
      "author_email": "mail@jhnet.co.uk",
      "files": [
        "plottie/cli.py",
        "plottie/plot_mode_heuristics.py",
        "tests/test_plot_mode_heuristics.py"
      ]
    },
    {
      "sha": "bbb490f3a1d9092e483c1bfbc696a2c878dcb3f8",
      "date": "2019-05-28T16:44:17Z",
      "author_login": "mossblaser",
      "author_name": "Jonathan Heathcote",
      "author_email": "mail@jhnet.co.uk",
      "files": [
        "plottie/line_ordering.py",
        "tests/test_line_ordering.py"
      ]
    },
    {
      "sha": "982d294238322daa4cebc2842077b4b0da097837",
      "date": "2019-05-28T16:02:05Z",
      "author_login": "mossblaser",
      "author_name": "Jonathan Heathcote",
      "author_email": "mail@jhnet.co.uk",
      "files": [
        "plottie/inside_first.py",
        "tests/test_inside_first.py"
      ]
    },
    {
      "sha": "98dbf5e96132d6f939cd955fbe8fa14594e8ad9b",
      "date": "2019-05-28T15:22:07Z",
      "author_login": "mossblaser",
      "author_name": "Jonathan Heathcote",
      "author_email": "mail@jhnet.co.uk",
      "files": [
        "plottie/svg_utils.py",
        "tests/test_svg_utils.py"
      ]
    },
    {
      "sha": "9888cea832995d0b2b800ca222ec289babf6b5d7",
      "date": "2019-05-27T18:56:05Z",
      "author_login": "mossblaser",
      "author_name": "Jonathan Heathcote",
      "author_email": "mail@jhnet.co.uk",
      "files": [
        "plottie/svg_utils.py",
        "tests/test_svg_utils.py"
      ]
    },
    {
      "sha": "d7a60bea620bcab85176f065834c6430eacbcedb",
      "date": "2019-01-30T17:32:40Z",
      "author_login": "mossblaser",
      "author_name": "Jonathan Heathcote",
      "author_email": "mail@jhnet.co.uk",
      "files": [
        "plottie/regmarks.py",
        "tests/test_regmarks.py"
      ]
    },
    {
      "sha": "e0db5dd0a96496d62ecd45cb4496cc748dd0ec0e",
      "date": "2019-01-30T16:28:09Z",
      "author_login": "mossblaser",
      "author_name": "Jonathan Heathcote",
      "author_email": "mail@jhnet.co.uk",
      "files": [
        "plottie/regmarks.py",
        "tests/test_regmarks.py"
      ]
    },
    {
      "sha": "8654e12a008ed817611a33a84dfe6a0a6a5ff3a6",
      "date": "2019-01-30T16:23:15Z",
      "author_login": "mossblaser",
      "author_name": "Jonathan Heathcote",
      "author_email": "mail@jhnet.co.uk",
      "files": [
        "plottie/regmarks.py",
        "tests/test_regmarks.py"
      ]
    },
    {
      "sha": "03d520db33e4fdac98ba653e921f562c7119b9dc",
      "date": "2019-01-29T16:34:00Z",
      "author_login": "mossblaser",
      "author_name": "Jonathan Heathcote",
      "author_email": "mail@jhnet.co.uk",
      "files": [
        ".gitignore",
        "README.md",
        "plottie/__init__.py",
        "plottie/cli.py",
        "plottie/css_colour_names.py",
        "plottie/regmarks.py",
        "plottie/svg_utils.py",
        "plottie/version.py",
        "plottie/xml_utils.py",
        "setup.py",
        "tests/test_regmarks.py",
        "tests/test_svg_utils.py",
        "tests/test_xml_utils.py"
      ]
    }
  ]
}